doc/markup.py
doc/scoop-prepare-bibtex-file.pdf
doc/scoop-template-engine.pdf
spbf/__init__.py
spbf/__main__.py
ste/__init__.py
ste/__main__.py
ste/letters/letters.py
ste/letters/scrartcl/template-letter-scrartcl.tex
ste/letters/scrlttr2/template-letter-scrlttr2.tex
ste/manuscripts/manuscripts.py
ste/manuscripts/ACS/init.py
ste/manuscripts/ACS/postpreamble-aabmcb.sty
ste/manuscripts/ACS/postpreamble-aaembp.sty
ste/manuscripts/ACS/postpreamble-aaemcq.sty
ste/manuscripts/ACS/postpreamble-aamick.sty
ste/manuscripts/ACS/postpreamble-aanmf6.sty
ste/manuscripts/ACS/postpreamble-aapmcd.sty
ste/manuscripts/ACS/postpreamble-aastgj.sty
ste/manuscripts/ACS/postpreamble-abmcb8.sty
ste/manuscripts/ACS/postpreamble-abseba.sty
ste/manuscripts/ACS/postpreamble-acbcct.sty
ste/manuscripts/ACS/postpreamble-accacs.sty
ste/manuscripts/ACS/postpreamble-achre4.sty
ste/manuscripts/ACS/postpreamble-achsc5.sty
ste/manuscripts/ACS/postpreamble-acncdm.sty
ste/manuscripts/ACS/postpreamble-acsccc.sty
ste/manuscripts/ACS/postpreamble-acscii.sty
ste/manuscripts/ACS/postpreamble-acsodf.sty
ste/manuscripts/ACS/postpreamble-aeacb3.sty
ste/manuscripts/ACS/postpreamble-aeacc4.sty
ste/manuscripts/ACS/postpreamble-aeecco.sty
ste/manuscripts/ACS/postpreamble-aelccp.sty
ste/manuscripts/ACS/postpreamble-aesccq.sty
ste/manuscripts/ACS/postpreamble-aewcaa.sty
ste/manuscripts/ACS/postpreamble-afsthl.sty
ste/manuscripts/ACS/postpreamble-aidcbc.sty
ste/manuscripts/ACS/postpreamble-amacgu.sty
ste/manuscripts/ACS/postpreamble-amachv.sty
ste/manuscripts/ACS/postpreamble-amclct.sty
ste/manuscripts/ACS/postpreamble-amlccd.sty
ste/manuscripts/ACS/postpreamble-amlcef.sty
ste/manuscripts/ACS/postpreamble-amrcda.sty
ste/manuscripts/ACS/postpreamble-anaccx.sty
ste/manuscripts/ACS/postpreamble-ancac3.sty
ste/manuscripts/ACS/postpreamble-ancham.sty
ste/manuscripts/ACS/postpreamble-aoiab5.sty
ste/manuscripts/ACS/postpreamble-apaccd.sty
ste/manuscripts/ACS/postpreamble-apcach.sty
ste/manuscripts/ACS/postpreamble-apchd5.sty
scoop_template_engine-1.5.3.dist-info/LICENSE
scoop_template_engine-1.5.3.dist-info/METADATA
scoop_template_engine-1.5.3.dist-info/WHEEL
scoop_template_engine-1.5.3.dist-info/entry_points.txt
scoop_template_engine-1.5.3.dist-info/top_level.txt
scoop_template_engine-1.5.3.dist-info/RECORD
