Metadata-Version: 2.2
Name: scoop-template-engine
Version: 1.5.3
Summary: Prepare scientific journal publications and other documents in LaTeX
Author-email: Roland Herzog <roland.herzog@iwr.uni-heidelberg.de>
Project-URL: homepage, https://gitlab.com/scoopgroup-public/scoop-template-engine
Project-URL: repository, https://gitlab.com/scoopgroup-public/scoop-template-engine
Project-URL: issues, https://gitlab.com/scoopgroup-public/scoop-template-engine/issues
Project-URL: changelog, https://gitlab.com/scoopgroup-public/scoop-template-engine/-/blob/main/CHANGELOG.md
Keywords: template engine,LaTeX,scientific publishing,journals
Classifier: Programming Language :: Python :: 3 :: Only
Classifier: Programming Language :: Python :: 3.9
Classifier: Programming Language :: Python :: 3.10
Classifier: Programming Language :: Python :: 3.11
Classifier: License :: OSI Approved :: MIT License
Classifier: Operating System :: OS Independent
Classifier: Development Status :: 5 - Production/Stable
Classifier: Intended Audience :: Science/Research
Classifier: Intended Audience :: Education
Classifier: Topic :: Text Editors :: Text Processing
Classifier: Topic :: Text Processing :: Markup :: LaTeX
Classifier: Topic :: Utilities
Requires-Python: >=3.9
License-File: LICENSE
Requires-Dist: bibtexparser==2.0.0b7
Requires-Dist: cloudscraper>=1.2.68
Requires-Dist: numpy>=1.0.0
Requires-Dist: packaging>=23.0.0
Requires-Dist: patch>=1.16
Requires-Dist: pyyaml>=6.0
Requires-Dist: requests>=2.9.2
Requires-Dist: scipy>=1.0.0
Requires-Dist: setuptools-git-versioning>=1.9.0
